asyncapi_generator/__init__.py
asyncapi_generator-0.1.0.dist-info/LICENSE
asyncapi_generator-0.1.0.dist-info/WHEEL
asyncapi_generator-0.1.0.dist-info/METADATA
asyncapi_generator-0.1.0.dist-info/RECORD
